pyrrha_mapper/__init__.py
pyrrha_mapper/__main__.py
pyrrha_mapper/exceptions.py
pyrrha_mapper/py.typed
pyrrha_mapper/types.py
pyrrha_mapper/common/__init__.py
pyrrha_mapper/common/filesystem_mapper.py
pyrrha_mapper/common/objects.py
pyrrha_mapper/exedecomp/__init__.py
pyrrha_mapper/exedecomp/binmapper.py
pyrrha_mapper/exedecomp/decompile.py
pyrrha_mapper/fs/__init__.py
pyrrha_mapper/fs/imports_mapper.py
pyrrha_mapper/intercg/__init__.py
pyrrha_mapper/intercg/fwmapper.py
pyrrha_mapper/intercg/loader.py
pyrrha_mapper-1.0.1.dist-info/licenses/LICENSE
pyrrha_mapper-1.0.1.dist-info/METADATA
pyrrha_mapper-1.0.1.dist-info/WHEEL
pyrrha_mapper-1.0.1.dist-info/entry_points.txt
pyrrha_mapper-1.0.1.dist-info/top_level.txt
pyrrha_mapper-1.0.1.dist-info/RECORD
