Metadata-Version: 2.4
Name: pyrrha-mapper
Version: 1.0.1
Summary: A mapper collection for firmware analysis
Author-email: Eloïse Brocas <ebrocas@quarkslab.com>, Robin David <rdavid@quarkslab.com>
License: Apache License 2.0
Project-URL: Homepage, https://github.com/quarkslab/pyrrha
Project-URL: Source, https://github.com/quarkslab/pyrrha
Project-URL: Tracker, https://github.com/quarkslab/pyrrha/issues
Project-URL: Changelog, https://github.com/quarkslab/pyrrha/CHANGELOG.md
Classifier: Development Status :: 4 - Beta
Classifier: Programming Language :: Python :: 3.10
Classifier: Programming Language :: Python :: 3.11
Classifier: Programming Language :: Python :: 3.12
Classifier: Programming Language :: Python :: 3.13
Classifier: Operating System :: POSIX :: Linux
Classifier: Operating System :: Microsoft :: Windows
Classifier: Topic :: Security
Classifier: Environment :: Console
Requires-Python: >=3.10
License-File: LICENSE
Requires-Dist: click
Requires-Dist: coloredlogs
Requires-Dist: lief>=0.15.0
Requires-Dist: numbat>=0.2.6
Requires-Dist: pydantic
Requires-Dist: rich
Requires-Dist: quokka-project
Requires-Dist: idascript<=0.3.1
Provides-Extra: doc
Requires-Dist: black; extra == "doc"
Requires-Dist: mkdocs; extra == "doc"
Requires-Dist: mkdocs-autorefs; extra == "doc"
Requires-Dist: mkdocs-glightbox; extra == "doc"
Requires-Dist: mkdocs-material[imaging]; extra == "doc"
Requires-Dist: mkdocs-section-index; extra == "doc"
Requires-Dist: mike; extra == "doc"
Requires-Dist: pymdown-extensions; extra == "doc"
Provides-Extra: linting
Requires-Dist: ruff; extra == "linting"
Provides-Extra: test
Requires-Dist: pytest; extra == "test"
Requires-Dist: pytest-cov; extra == "test"
Provides-Extra: typechecking
Requires-Dist: mypy; extra == "typechecking"
Dynamic: license-file
